{"singlePage": [], "startSite": "", "filingNum": "", "onePageListNum": 15, "commentLabelColor": "#006b75", "yearColorList": ["#bc4c00", "#0969da", "#1f883d", "#A333D0"], "i18n": "CN", "themeMode": "manual", "dayTheme": "light", "nightTheme": "dark", "urlMode": "pinyin", "script": "", "style": "", "head": "", "indexScript": "", "indexStyle": "", "bottomText": "", "showPostSource": 1, "iconList": {}, "UTC": 8, "rssSplit": "sentence", "exlink": {}, "needComment": 1, "allHead": "", "title": "Blog Title", "subTitle": "Blog description", "avatarUrl": "https://github.githubassets.com/favicons/favicon.svg", "GMEEK_VERSION": "last", "postListJson": {"P1": {"htmlDir": "docs/post/kai-shi-shi-yong-blog.html", "labels": ["\u6280\u672f"], "postTitle": "\u5f00\u59cb\u4f7f\u7528blog", "postUrl": "post/kai-shi-shi-yong-blog.html", "postSourceUrl": "https://github.com/skyseawin/skyseawind.github.io/issues/1", "commentNum": 1, "wordCount": 3, "description": "\u6d4b\u8bd5\u4e2d\u3002", "top": 0, "createdAt": 1711596958, "style": "", "script": "", "head": "", "ogImage": "https://github.githubassets.com/favicons/favicon.svg", "createdDate": "2024-03-28", "dateLabelColor": "#bc4c00"}, "P2": {"htmlDir": "docs/post/ce-shi-3.html", "labels": ["\u6280\u672f"], "postTitle": "\u6d4b\u8bd53", "postUrl": "post/ce-shi-3.html", "postSourceUrl": "https://github.com/skyseawin/skyseawind.github.io/issues/2", "commentNum": 0, "wordCount": 63, "description": "foooooooooooooooooooooooooooooooooooooooooooooooooooooooooooooo\u3002", "top": 0, "createdAt": 1713865739, "style": "", "script": "", "head": "", "ogImage": "https://github.githubassets.com/favicons/favicon.svg", "createdDate": "2024-04-23", "dateLabelColor": "#bc4c00"}}, "singeListJson": {}, "labelColorDict": {"bug": "#d73a4a", "documentation": "#0075ca", "duplicate": "#cfd3d7", "enhancement": "#a2eeef", "good first issue": "#7057ff", "help wanted": "#008672", "invalid": "#e4e669", "question": "#d876e3", "wontfix": "#ffffff", "\u6280\u672f": "#e99695"}, "displayTitle": "Blog Title", "faviconUrl": "https://github.githubassets.com/favicons/favicon.svg", "ogImage": "https://github.githubassets.com/favicons/favicon.svg", "primerCSS": "<link href='https://mirrors.sustech.edu.cn/cdnjs/ajax/libs/Primer/21.0.7/primer.css' rel='stylesheet' />", "homeUrl": "https://skyseawin.github.io/skyseawind.github.io", "prevUrl": "disabled", "nextUrl": "disabled"}